llmify/__init__.py
llmify/core/__init__.py
llmify/core/gatekeeper/__init__.py
llmify/core/gatekeeper/gatekeeper.py
llmify/core/models/model.pkl
llmify/llms/__init__.py
llmify/utils/__init__.py
llmify/utils/openai.py
llmify/utils/openai/__init__.py
llmify/utils/openai/mappers.py
llmify/utils/openai/tools.py
llmify/vector_dbs/__init__.py
llmify-0.1.2.1.dist-info/METADATA
llmify-0.1.2.1.dist-info/WHEEL
llmify-0.1.2.1.dist-info/top_level.txt
llmify-0.1.2.1.dist-info/RECORD
